{
  "companyName": "Dolimiti Steel Roofing",
  "shortName": "Dolimiti",
  "serviceMain": "Steel Roofing",
  "domain": "dolimitisteelroofing.com",
  "canonicalBase": "https://dolimitisteelroofing.com",
  "phone": "(888) 555-7820",
  "phoneClean": "8885557820",
  "email": "info@dolimitisteelroofing.com",
  "tagline": "Premium Steel Roofing Built to Last",
  "description": "Dolimiti Steel Roofing provides expert steel and metal roofing installation, repair, and replacement services. Licensed, insured, and delivering durable, energy-efficient roofing systems nationwide.",
  "yearsInBusiness": "15+",
  "foundedYear": 2010,
  "address": {
    "street": "",
    "city": "",
    "state": "",
    "zip": ""
  },
  "hours": {
    "weekdays": "7:00 AM - 7:00 PM",
    "saturday": "8:00 AM - 5:00 PM",
    "sunday": "Emergency Only",
    "emergency": "24/7"
  },
  "social": {
    "facebook": "",
    "instagram": "",
    "twitter": "",
    "linkedin": "",
    "youtube": ""
  },
  "colors": {
    "primary": "#1e3a5f",
    "primaryLight": "#2d5a8a",
    "primaryDark": "#0f1f33",
    "accent": "#d97706",
    "accentLight": "#f59e0b",
    "accentDark": "#b45309",
    "background": "#ffffff",
    "backgroundAlt": "#f8fafc",
    "text": "#1f2937",
    "textLight": "#6b7280"
  },
  "trustBadges": [
    {
      "title": "Licensed & Insured",
      "description": "Fully licensed, bonded, and insured steel roofing specialists.",
      "icon": "shield-check"
    },
    {
      "title": "Metal Roofing Experts",
      "description": "Specialized in standing seam and high-performance steel roofing systems.",
      "icon": "clock"
    },
    {
      "title": "Free Estimates",
      "description": "No-obligation quotes with transparent, upfront pricing.",
      "icon": "calculator"
    },
    {
      "title": "Long-Term Warranty",
      "description": "We stand behind every steel roof with material and workmanship warranties.",
      "icon": "star"
    }
  ],
  "navigation": {
    "main": [
      { "href": "/", "label": "Home" },
      { "href": "/locations", "label": "Locations", "hideOnSubdomain": true },
      { "href": "/services", "label": "Services" },
      { "href": "/about", "label": "About" },
      { "href": "/contact", "label": "Contact" }
    ],
    "ctaButton": { "href": "/contact", "label": "Get a Quote" }
  },
  "process": [
    {
      "step": 1,
      "title": "Free Roof Inspection",
      "description": "We thoroughly inspect your roof structure and assess your steel roofing needs."
    },
    {
      "step": 2,
      "title": "Detailed Proposal",
      "description": "Receive a transparent, no-surprise estimate tailored to your project."
    },
    {
      "step": 3,
      "title": "Project Scheduling",
      "description": "We schedule your installation at a convenient time and arrive prepared."
    },
    {
      "step": 4,
      "title": "Precision Installation",
      "description": "Our certified team installs your steel roofing system with exact manufacturer specifications."
    },
    {
      "step": 5,
      "title": "Final Quality Check",
      "description": "We conduct a full walkthrough to ensure structural integrity and your complete satisfaction."
    }
  ]
}